{"type":"FeatureCollection","metadata":{"station_locator_url":"https://afdc.energy.gov/stations/","total_results":14782,"station_counts":{"total":41858,"fuels":{"BD":{"total":0},"E85":{"total":286},"ELEC":{"total":41572,"stations":{"total":14496}},"HY":{"total":0},"LNG":{"total":0},"CNG":{"total":0},"LPG":{"total":0}}}},"features":[{"type":"Feature","geometry":{"type":"Point","coordinates":[-118.3879713743439,34.2483191527193]},"properties":{"access_code":"private","access_days_time":"Fleet use only","access_detail_code":null,"cards_accepted":null,"date_last_confirmed":"2021-07-14","expected_date":null,"fuel_type_code":"ELEC","groups_with_access_code":"Private","id":1517,"open_date":"1999-10-15","owner_type_code":"LG","status_code":"E","station_name":"LADWP - Truesdale Center","station_phone":null,"updated_at":"2022-02-10T19:42:29Z","facility_type":"UTILITY","geocode_status":"GPS","city":"Sun Valley","intersection_directions":null,"plus4":null,"state":"CA","street_address":"11797 Truesdale St","zip":"91352","country":"US","bd_blends":null,"cng_dispenser_num":null,"cng_fill_type_code":null,"cng_psi":null,"cng_renewable_source":null,"cng_total_compression":null,"cng_total_storage":null,"cng_vehicle_class":null,"e85_blender_pump":null,"e85_other_ethanol_blends":null,"ev_connector_types":["CHADEMO","J1772","J1772COMBO"],"ev_dc_fast_num":3,"ev_level1_evse_num":null,"ev_level2_evse_num":39,"ev_network":"Non-Networked","ev_network_web":null,"ev_other_evse":null,"ev_pricing":null,"ev_renewable_source":null,"hy_is_retail":null,"hy_pressures":null,"hy_standards":null,"hy_status_link":null,"lng_renewable_source":null,"lng_vehicle_class":null,"lpg_primary":null,"lpg_nozzle_types":null,"ng_fill_type_code":null,"ng_psi":null,"ng_vehicle_class":null,"access_days_time_fr":null,"intersection_directions_fr":null,"bd_blends_fr":null,"groups_with_access_code_fr":"Privé","ev_pricing_fr":null}},{"type":"Feature","geometry":{"type":"Point","coordinates":[-118.448504,34.052542]},"properties":{"access_code":"private","access_days_time":null,"access_detail_code":null,"cards_accepted":null,"date_last_confirmed":"2021-07-14","expected_date":null,"fuel_type_code":"ELEC","groups_with_access_code":"Private","id":1519,"open_date":"2020-02-28","owner_type_code":"LG","status_code":"E","station_name":"LADWP - West LA District Office","station_phone":null,"updated_at":"2022-02-10T19:42:29Z","facility_type":"UTILITY","geocode_status":"200-8","city":"Los Angeles","intersection_directions":null,"plus4":null,"state":"CA","street_address":"1394 S Sepulveda Blvd","zip":"90024","country":"US","bd_blends":null,"cng_dispenser_num":null,"cng_fill_type_code":null,"cng_psi":null,"cng_renewable_source":null,"cng_total_compression":null,"cng_total_storage":null,"cng_vehicle_class":null,"e85_blender_pump":null,"e85_other_ethanol_blends":null,"ev_connector_types":["J1772"],"ev_dc_fast_num":null,"ev_level1_evse_num":null,"ev_level2_evse_num":4,"ev_network":"Non-Networked","ev_network_web":null,"ev_other_evse":null,"ev_pricing":"Free","ev_renewable_source":null,"hy_is_retail":null,"hy_pressures":null,"hy_standards":null,"hy_status_link":null,"lng_renewable_source":null,"lng_vehicle_class":null,"lpg_primary":null,"lpg_nozzle_types":null,"ng_fill_type_code":null,"ng_psi":null,"ng_vehicle_class":null,"access_days_time_fr":null,"intersection_directions_fr":null,"bd_blends_fr":null,"groups_with_access_code_fr":"Privé","ev_pricing_fr":null}}]}